tree_sitter_epics_msi_substitution/__init__.py
tree_sitter_epics_msi_substitution/__init__.pyi
tree_sitter_epics_msi_substitution/_binding.abi3.so
tree_sitter_epics_msi_substitution/binding.c
tree_sitter_epics_msi_substitution/py.typed
tree_sitter_epics_msi_substitution/queries/highlights.scm
tree_sitter_epics_msi_substitution/queries/injections.scm
tree_sitter_epics_msi_substitution-0.2.1.dist-info/METADATA
tree_sitter_epics_msi_substitution-0.2.1.dist-info/WHEEL
tree_sitter_epics_msi_substitution-0.2.1.dist-info/top_level.txt
tree_sitter_epics_msi_substitution-0.2.1.dist-info/RECORD
tree_sitter_epics_msi_substitution-0.2.1.dist-info/licenses/LICENSE
